rpu/__init__.py
rpu/__main__.py
rpu/chars.py
rpu/cli.py
rpu/consts.py
rpu/dicts.py
rpu/grammar.py
rpu/iterables.py
rpu/numbers.py
rpu/objects.py
rpu/librarys/__init__.py
rpu-0.0.4.dist-info/LICENSE
rpu-0.0.4.dist-info/METADATA
rpu-0.0.4.dist-info/WHEEL
rpu-0.0.4.dist-info/top_level.txt
rpu-0.0.4.dist-info/RECORD
