Metadata-Version: 2.1
Name: rpu
Version: 0.0.4
Summary: Random python utilities
Home-page: https://github.com/cibere/rpu
Author: cibere
Author-email: cibere.dev@gmail.com
License: MIT
Project-URL: Code, https://github.com/cibere/rpu
Project-URL: Issue tracker, https://github.com/cibere/rpu/issues
Project-URL: Discord/Support Server, https://discord.gg/2MRrJvP42N
Requires-Python: >=3.9
License-File: LICENSE
